{
    "version": "0.1.52",
    "architecture": {
        "32bit": {
            "url": "https://github.com/OpenIoTHub/gateway-go/releases/download/v0.1.52/gateway-go_0.1.52_Windows_i386.tar.gz",
            "bin": [
                "gateway-go.exe"
            ],
            "hash": "2b414000e5272254113c8c72c0e175b937452317242e97e7b8c7d01ffdf3c240"
        },
        "64bit": {
            "url": "https://github.com/OpenIoTHub/gateway-go/releases/download/v0.1.52/gateway-go_0.1.52_Windows_x86_64.tar.gz",
            "bin": [
                "gateway-go.exe"
            ],
            "hash": "928d39198aeeda06a0b4589972dc733bc4a466054d62e4a0df326019f1fb99ce"
        }
    },
    "homepage": "http://github.com/OpenIoTHub",
    "license": "MIT",
    "description": "OpenIoTHub GateWay"
}