{
    "version": "0.1.35",
    "architecture": {
        "32bit": {
            "url": "https://github.com/OpenIoTHub/gateway-go/releases/download/v0.1.35/gateway-go_0.1.35_Windows_i386.tar.gz",
            "bin": [
                "gateway-go.exe"
            ],
            "hash": "8b81ab5963739251cc4f1757d7e148c841156e45366e6fc7226b20983e8c98cb"
        },
        "64bit": {
            "url": "https://github.com/OpenIoTHub/gateway-go/releases/download/v0.1.35/gateway-go_0.1.35_Windows_x86_64.tar.gz",
            "bin": [
                "gateway-go.exe"
            ],
            "hash": "6d58bca470359d768c5c8d9119fd2fb5e8e7964b16d7d3afe8815839517f0f79"
        }
    },
    "homepage": "http://github.com/OpenIoTHub",
    "license": "MIT",
    "description": "OpenIoTHub GateWay"
}