{
    "version": "0.1.92",
    "architecture": {
        "32bit": {
            "url": "https://github.com/OpenIoTHub/gateway-go/releases/download/v0.1.92/gateway-go_0.1.92_Windows_i386.tar.gz",
            "bin": [
                "gateway-go.exe"
            ],
            "hash": "ac11c27ef2563c586493fb7ee87c49da9fe2efe86beeffcc34f42aadbcabde63"
        },
        "64bit": {
            "url": "https://github.com/OpenIoTHub/gateway-go/releases/download/v0.1.92/gateway-go_0.1.92_Windows_x86_64.tar.gz",
            "bin": [
                "gateway-go.exe"
            ],
            "hash": "ba69fc4ef5f84574b2d5fcdcf6f694b02eed47e87873a4722089dce531b14841"
        }
    },
    "homepage": "http://github.com/OpenIoTHub",
    "license": "MIT",
    "description": "OpenIoTHub GateWay"
}